hashpw/__init__.py
hashpw/cli.py
hashpw/errors.py
hashpw/structure.py
hashpw/utils.py
hashpw/algs/ApacheMD5.py
hashpw/algs/ApacheSHA1.py
hashpw/algs/BCrypt.py
hashpw/algs/BasicMD5.py
hashpw/algs/Blowfish.py
hashpw/algs/Crypt.py
hashpw/algs/ExtDes.py
hashpw/algs/LDAPv2SMD5.py
hashpw/algs/LDAPv2SSHA256.py
hashpw/algs/LDAPv2SSHA512.py
hashpw/algs/MD5.py
hashpw/algs/MySqlSHA1.py
hashpw/algs/OldPassword.py
hashpw/algs/PBKDF2.py
hashpw/algs/PhpBB3.py
hashpw/algs/Phpass.py
hashpw/algs/SHA256.py
hashpw/algs/SHA512.py
hashpw/algs/SSHA.py
hashpw/algs/__init__.py
hashpw/contrib/__init__.py
hashpw/contrib/tback.py
hashpw-2.6.0.dist-info/LICENSE
hashpw-2.6.0.dist-info/METADATA
hashpw-2.6.0.dist-info/WHEEL
hashpw-2.6.0.dist-info/entry_points.txt
hashpw-2.6.0.dist-info/top_level.txt
hashpw-2.6.0.dist-info/RECORD
