Metadata-Version: 2.1
Name: hashpw
Version: 2.6.0
Summary: Universal password hash generator and verifier
Home-page: https://github.com/unixnut/hashpw
Author: Alastair Irvine
Author-email: alastair@plug.org.au
License: UNKNOWN
Keywords: password,hash,cli
Platform: UNKNOWN
Classifier: Development Status :: 3 - Alpha
Classifier: Intended Audience :: Developers
Classifier: License :: OSI Approved :: GNU General Public License v3 (GPLv3)
Classifier: Natural Language :: English
Classifier: Programming Language :: Python :: 3
Classifier: Programming Language :: Python :: 3.5
Classifier: Programming Language :: Python :: 3.6
Classifier: Programming Language :: Python :: 3.7
Classifier: Programming Language :: Python :: 3.8
Classifier: Programming Language :: Python :: 3.9
Classifier: Programming Language :: Python :: 3.10
Requires-Python: >=3.5
Requires-Dist: bcrypt (==4.0.1)
Requires-Dist: passlib
